setup.py
python_terminal_alpha/__init__.py
python_terminal_alpha/terminal.py
python_terminal_alpha.egg-info/PKG-INFO
python_terminal_alpha.egg-info/SOURCES.txt
python_terminal_alpha.egg-info/dependency_links.txt
python_terminal_alpha.egg-info/not-zip-safe
python_terminal_alpha.egg-info/top_level.txt